proxy_requests/__init__.py
proxy_requests/proxy_requests.py
proxy_requests-0.2.1.dist-info/METADATA
proxy_requests-0.2.1.dist-info/RECORD
proxy_requests-0.2.1.dist-info/WHEEL
proxy_requests-0.2.1.dist-info/top_level.txt
