Metadata-Version: 2.1
Name: proxy-requests
Version: 0.2.1
Summary: A wrapper for the Python 3 requests module
Home-page: https://github.com/rootVIII/proxy_requests
Author: James Loye Colley
License: UNKNOWN
Platform: UNKNOWN
Classifier: Programming Language :: Python :: 3
Classifier: License :: OSI Approved :: MIT License
Classifier: Operating System :: OS Independent
Requires-Dist: requests
